<Properties StartupConfiguration="{43CD8F3F-80CE-BD30-293C-C814F25DB887}|">
  <MonoDevelop.Ide.Workbench>
    <Pads>
      <Pad Id="ProjectPad">
        <State name="__root__">
          <Node name="Feed the Monster" expanded="True">
            <Node name="Assets" expanded="True">
              <Node name="Resources" expanded="True">
                <Node name="Gameplay" expanded="True">
                  <Node name="Levels" expanded="True">
                    <Node name="level0.xml" selected="True" />
                  </Node>
                </Node>
              </Node>
              <Node name="Tracing" expanded="True">
                <Node name="Scripts" expanded="True">
                  <Node name="Utility" expanded="True" />
                </Node>
              </Node>
            </Node>
          </Node>
        </State>
      </Pad>
      <Pad Id="ClassPad">
        <State name="__root__">
          <Node name="Feed the Monster" expanded="True" selected="True" />
        </State>
      </Pad>
      <Pad Id="MonoDevelop.Debugger.WatchPad">
        <State />
      </Pad>
      <Pad Id="MonoDevelop.UnitTesting.TestPad">
        <State name="__root__">
          <Node name="Feed the Monster" expanded="True" selected="True" />
        </State>
      </Pad>
    </Pads>
  </MonoDevelop.Ide.Workbench>
  <MonoDevelop.Ide.Workspace ActiveConfiguration="Debug" />
  <MonoDevelop.Ide.DebuggingService.Breakpoints>
    <BreakpointStore />
  </MonoDevelop.Ide.DebuggingService.Breakpoints>
  <MonoDevelop.Ide.DebuggingService.PinnedWatches />
  <MultiItemStartupConfigurations />
  <MonoDevelop.Ide.ItemProperties.Feed_220the_220Monster PreferredExecutionTarget="Unity.Editor" />
</Properties>