<XMLLevel CollectableMonster="" HideCallout="-1" LettersGroup="16" SegmentTime="11" StoneType="1" monsterInputType="Word">
  <Segments>
  		<Segment SegmentTime="10" spawnIds="20,75,15,23,74,14,11,12,60">
		
      	<MonsterRequiredLetters>
			<string>w</string><string>e</string><string>d</string></MonsterRequiredLetters>
	  	<MonsterAllLetters>
	  	</MonsterAllLetters>
	  	<Stones>
			<string>e</string><string>n</string><string>d</string><string>u</string><string>w</string><string>f</string></Stones>
	</Segment>
    <Segment SegmentTime="10" spawnIds="20,75,15,23,74,14,11,12,60">
    	
    	<MonsterRequiredLetters>
    		<string>t</string><string>e</string><string>d</string></MonsterRequiredLetters>
    	<MonsterAllLetters>
    	</MonsterAllLetters>
    	<Stones>
    		<string>e</string><string>k</string><string>t</string><string>s</string><string>d</string><string>n</string></Stones>
	</Segment>
	<Segment SegmentTime="10" spawnIds="20,75,15,23,74,14,11,12,60">
		
      	<MonsterRequiredLetters>
			<string>j</string><string>e</string><string>t</string></MonsterRequiredLetters>
	  	<MonsterAllLetters>
	  	</MonsterAllLetters>
	  	<Stones>
	        <string>t</string><string>x</string><string>e</string><string>l</string><string>j</string><string>v</string></Stones>
    </Segment>
	<Segment SegmentTime="10" spawnIds="20,75,15,23,74,14,11,12,60">
		
		<MonsterRequiredLetters>
			<string>d</string><string>e</string><string>n</string></MonsterRequiredLetters>
	  	<MonsterAllLetters>
	  	</MonsterAllLetters>
	  	<Stones>
        	<string>n</string><string>r</string><string>e</string><string>y</string><string>d</string><string>f</string></Stones>
    </Segment>


	<Segment SegmentTime="10" spawnIds="20,75,15,23,74,14,11,12,60">
		
      	<MonsterRequiredLetters>
			<string>w</string><string>e</string><string>t</string></MonsterRequiredLetters>
	  	<MonsterAllLetters>
	  	</MonsterAllLetters>
	  	<Stones>
	        <string>t</string><string>k</string><string>w</string><string>i</string><string>e</string><string>c</string></Stones>
	</Segment>
  </Segments>
</XMLLevel>